setup.cfg
setup.py
muqfatc/__init__.py
muqfatc/imageanalysis.py
muqfatc/lineagegrowth.py
muqfatc/pingrowth.py
muqfatc/resratemap.py
muqfatc.egg-info/PKG-INFO
muqfatc.egg-info/SOURCES.txt
muqfatc.egg-info/dependency_links.txt
muqfatc.egg-info/not-zip-safe
muqfatc.egg-info/top_level.txt