Metadata-Version: 1.0
Name: muqfatc
Version: 0.1
Summary: Image analysis tool for analysing QFA (Addinall et al., 2011) cultures on a high-throughput level. Single lineage and pin population growth is catpured.
Home-page: https://github.com/lwlss/discstoch
Author: Helena Herrmann
Author-email: h.herrmann2@gmail.com
License: MIT
Platform: UNKNOWN
